[
  {
    "id": "p1",
    "title": "Mount Astraeus & Mount Yorunova",
    "category": "Roblox Map",
    "description": "Map Roblox bertema pegunungan fantasi dengan environment design dan terrain custom.",
    "link": "https://www.roblox.com/users/4210208917/profile",
    "image": "",
    "year": "2023",
    "createdAt": "2026-07-03T00:00:00.000Z"
  },
  {
    "id": "p2",
    "title": "Exile Network",
    "category": "Minecraft Server",
    "description": "Server Minecraft publik yang aktif tahun 2020-2023 dengan ratusan pemain aktif.",
    "link": "https://youtu.be/ncNe-3r5V-w?si=jYkiTyZRu1cc4MvE",
    "image": "",
    "year": "2020-2023",
    "createdAt": "2026-07-03T00:00:00.000Z"
  },
  {
    "id": "p3",
    "title": "Caggy Shop",
    "category": "Website Development",
    "description": "Pembuatan website untuk kebutuhan jual-beli dan jasa digital lainnya.",
    "link": "https://caggyshop.xyz",
    "image": "",
    "year": "2024",
    "createdAt": "2026-07-03T00:00:00.000Z"
  }
]
